nbencdec/__init__.py
nbencdec/cli/__init__.py
nbencdec/cli/commands.py
nbencdec/exporters/__init__.py
nbencdec/exporters/encoded_python.py
nbencdec/exporters/filters.py
nbencdec/exporters/templates/encoded_python.tpl
nbencdec-0.0.4.dist-info/METADATA
nbencdec-0.0.4.dist-info/RECORD
nbencdec-0.0.4.dist-info/WHEEL
nbencdec-0.0.4.dist-info/entry_points.txt
nbencdec-0.0.4.dist-info/top_level.txt
